[{"message_id": 1, "sender_id": 5, "checked_by_id": 24, "text": "text1"}, {"message_id": 2, "sender_id": 10, "checked_by_id": 24, "text": "text2"}, {"message_id": 3, "sender_id": 7, "checked_by_id": 22, "text": "text3"}, {"message_id": 4, "sender_id": 11, "checked_by_id": 0, "text": "text4"}, {"message_id": 5, "sender_id": 9, "checked_by_id": 0, "text": "text5"}, {"message_id": 6, "sender_id": 7, "checked_by_id": 23, "text": "text6"}, {"message_id": 7, "sender_id": 5, "checked_by_id": 0, "text": "text7"}, {"message_id": 8, "sender_id": 11, "checked_by_id": 24, "text": "text8"}, {"message_id": 9, "sender_id": 2, "checked_by_id": 23, "text": "text9"}, {"message_id": 10, "sender_id": 4, "checked_by_id": 24, "text": "text10"}, {"message_id": 11, "sender_id": 7, "checked_by_id": 24, "text": "text11"}, {"message_id": 12, "sender_id": 7, "checked_by_id": 22, "text": "text12"}, {"message_id": 13, "sender_id": 7, "checked_by_id": 22, "text": "text13"}, {"message_id": 14, "sender_id": 2, "checked_by_id": 24, "text": "text14"}, {"message_id": 15, "sender_id": 4, "checked_by_id": 23, "text": "text15"}, {"message_id": 16, "sender_id": 11, "checked_by_id": 24, "text": "text16"}, {"message_id": 17, "sender_id": 7, "checked_by_id": 0, "text": "text17"}, {"message_id": 18, "sender_id": 10, "checked_by_id": 23, "text": "text18"}, {"message_id": 19, "sender_id": 6, "checked_by_id": 22, "text": "text19"}, {"message_id": 20, "sender_id": 9, "checked_by_id": 23, "text": "text20"}]